piblin/__init__.py
piblin/data/__init__.py
piblin/data/data_collections/__init__.py
piblin/data/data_collections/consistent_measurement_set.py
piblin/data/data_collections/data_collection_factory.py
piblin/data/data_collections/experiment.py
piblin/data/data_collections/experiment_set.py
piblin/data/data_collections/measurement.py
piblin/data/data_collections/measurement_set.py
piblin/data/data_collections/summary.py
piblin/data/data_collections/tabular_measurement_set.py
piblin/data/data_collections/tidy_measurement_set.py
piblin/data/datasets/__init__.py
piblin/data/datasets/linear_regions.py
piblin/data/datasets/roi.py
piblin/data/datasets/abc/__init__.py
piblin/data/datasets/abc/dataset.py
piblin/data/datasets/abc/dataset_factory.py
piblin/data/datasets/abc/split_datasets/__init__.py
piblin/data/datasets/abc/split_datasets/distribution.py
piblin/data/datasets/abc/split_datasets/histogram.py
piblin/data/datasets/abc/split_datasets/one_dimensional_composite_dataset.py
piblin/data/datasets/abc/split_datasets/one_dimensional_dataset.py
piblin/data/datasets/abc/split_datasets/three_dimensional_dataset.py
piblin/data/datasets/abc/split_datasets/two_dimensional_dataset.py
piblin/data/datasets/abc/split_datasets/zero_dimensional_dataset.py
piblin/data/datasets/abc/unambiguous_datasets/__init__.py
piblin/data/datasets/abc/unambiguous_datasets/one_dimensional_unambiguous_dataset.py
piblin/data/datasets/abc/unambiguous_datasets/unambiguous_dataset.py
piblin/dataio/__init__.py
piblin/dataio/data_collection_reader.py
piblin/dataio/metadata_converter.py
piblin/dataio/pandas.py
piblin/dataio/read_summary.py
piblin/dataio/fileio/__init__.py
piblin/dataio/fileio/autodetect.py
piblin/dataio/fileio/batch_conversion.py
piblin/dataio/fileio/binary.py
piblin/dataio/fileio/read/__init__.py
piblin/dataio/fileio/read/file_reader.py
piblin/dataio/fileio/read/file_reader_template.py
piblin/dataio/fileio/read/generic/__init__.py
piblin/dataio/fileio/read/generic/generic_csv.py
piblin-0.0.0a1.dist-info/LICENSE
piblin-0.0.0a1.dist-info/METADATA
piblin-0.0.0a1.dist-info/WHEEL
piblin-0.0.0a1.dist-info/top_level.txt
piblin-0.0.0a1.dist-info/RECORD
