Metadata-Version: 2.1
Name: piblin
Version: 0.0.0a1
Summary: Measurement data science functionality
Author: Matthew John Mills <mmills2@mmm.com>,
Requires-Dist: matplotlib <=3.9.2
Requires-Dist: numpy >=1.21
Requires-Dist: scipy
Provides-Extra: tests
Requires-Dist: pytest ; extra == 'tests'
Requires-Dist: pytest-mpl ; extra == 'tests'
Requires-Dist: pytest-cov ; extra == 'tests'
Requires-Dist: pytest-html ; extra == 'tests'
